{"model_id": "Model:CLEANER-KCL-3001", "title": "Barclays Computers (PVT) Ltd. - CLEANER-KCL-3001 - Opula KCL-3001 Cleaner (N/W)", "url": "http://www.barclays.lk/bc/itemdesc.asp?ic=40652&eq=&Tp=", "brand": null, "summary": "            Item Code:40652            Weight:638.00GMStock:NoModel:CLEANER-KCL-3001Categories:Cleaner", "price": "530.00", "specs": "Material: MicrofiberUse: universal cleanerFeature: Eco-friendlyAlcohol and ammonium: freeFeature1. Perfect to clean any washable or painted surface,help tp restire true color and appearance.2. Suitable for auto, boat, could be especially effective for cleaning vinyl and fabric upholstery, floor mats, carpets and chrome,and also for appliances, formica, bathroom, fixtures, asphalt or ceramic tile, painted walls, wall coverings, screens, window fans, porcelain, painted wood or metal.3. Removes soils and stains from vinel or fabric upholstery and from carpets.ComponentsCleaning (gel)solution: 650ml Eco-friendly foam cleaning agent brush:with or without ", "catogory": "Cleaner"}